README.md
setup.py
botchecker/__init__.py
botchecker/bots.py
botchecker/checker.py
botchecker/datastructures.py
steem_bot_checker.egg-info/PKG-INFO
steem_bot_checker.egg-info/SOURCES.txt
steem_bot_checker.egg-info/dependency_links.txt
steem_bot_checker.egg-info/top_level.txt