Metadata-Version: 1.0
Name: steem-bot-checker
Version: 0.0.1
Summary: A simple Python library to check a STEEM account operators a bot or not
Home-page: https://github.com/emre/botchecker
Author: emre yilmaz
Author-email: mail@emreyilmaz.me
License: MIT
Platform: UNKNOWN
